nmfprofiler/__init__.py
nmfprofiler/__main__.py
nmfprofiler/nmfprofiler.py
nmfprofiler/toyexample.py
nmfprofiler/utils/__init__.py
nmfprofiler/utils/validate_inputs.py
nmfprofiler-0.3.1.dist-info/licenses/LICENSE
nmfprofiler-0.3.1.dist-info/METADATA
nmfprofiler-0.3.1.dist-info/WHEEL
nmfprofiler-0.3.1.dist-info/entry_points.txt
nmfprofiler-0.3.1.dist-info/top_level.txt
nmfprofiler-0.3.1.dist-info/RECORD
