Metadata-Version: 2.4
Name: NMFProfiler
Version: 0.3.1
Summary: NMFProfiler: an integrative supervised Non-Negative Matrix Factorization to extract typical profiles of groups of interest combining two different datasets.
Author-email: Aurélie Mercadié <aurelie.mercadie@inrae.fr>, Eric Casellas <eric.casellas@inrae.fr>, Eléonore Gravier <eleonore.gravier@pierre-fabre.com>, Gwendal Josse <gwendal.josse@pierre-fabre.com>, Nathalie Vialaneix <nathalie.vialaneix@inrae.fr>, Céline Brouard <celine.brouard@inrae.fr>
Maintainer-email: Aurélie Mercadié <aurelie.mercadie@inrae.fr>
License: ﻿                    GNU GENERAL PUBLIC LICENSE
Project-URL: Homepage, https://forge.inrae.fr/omics-integration/nmfprofiler
Project-URL: Documentation, https://omics-integration.pages.mia.inra.fr/nmfprofiler
Project-URL: Changelog, https://forge.inrae.fr/omics-integration/nmfprofiler/-/blob/main/CHANGELOG.md
Keywords: NMF,omics integration,matrix factorization
Classifier: Intended Audience :: Science/Research
Classifier: License :: OSI Approved :: GNU General Public License v3 or later (GPLv3+)
Classifier: Operating System :: Microsoft :: Windows
Classifier: Operating System :: POSIX :: Linux
Classifier: Programming Language :: Python
Classifier: Programming Language :: Python :: 3
Classifier: Topic :: Scientific/Engineering :: Bio-Informatics
Classifier: Topic :: Scientific/Engineering :: Mathematics
Requires-Python: >=3.8.10
License-File: LICENSE
Requires-Dist: matplotlib>=3.1.2
Requires-Dist: numpy>=1.23.2
Requires-Dist: pandas>=1.4.3
Requires-Dist: scikit-learn>=1.2.1
Requires-Dist: seaborn>=0.11.2
Requires-Dist: statsmodels>=0.14.0
Provides-Extra: dev
Requires-Dist: black; extra == "dev"
Requires-Dist: bump2version; extra == "dev"
Requires-Dist: isort; extra == "dev"
Requires-Dist: pip-tools; extra == "dev"
Requires-Dist: pytest; extra == "dev"
Dynamic: license-file
